piphttps/__init__.py
piphttps/__main__.py
piphttps-1.dist-info/METADATA
piphttps-1.dist-info/WHEEL
piphttps-1.dist-info/top_level.txt
piphttps-1.dist-info/RECORD
